girder_oauth/__init__.py
girder_oauth/rest.py
girder_oauth/settings.py
girder_oauth/providers/__init__.py
girder_oauth/providers/base.py
girder_oauth/providers/bitbucket.py
girder_oauth/providers/box.py
girder_oauth/providers/cilogon.py
girder_oauth/providers/github.py
girder_oauth/providers/globus.py
girder_oauth/providers/google.py
girder_oauth/providers/linkedin.py
girder_oauth/providers/microsoft.py
girder_oauth/web_client/dist/girder-plugin-oauth.umd.cjs
girder_oauth/web_client/dist/style.css
girder_oauth-5.0.0a14.dev27.dist-info/METADATA
girder_oauth-5.0.0a14.dev27.dist-info/WHEEL
girder_oauth-5.0.0a14.dev27.dist-info/entry_points.txt
girder_oauth-5.0.0a14.dev27.dist-info/top_level.txt
girder_oauth-5.0.0a14.dev27.dist-info/RECORD
